LICENSE
MANIFEST.in
README.md
requirements.txt
setup.py
theeng/__init__.py
theeng/theeng.py
theeng.egg-info/PKG-INFO
theeng.egg-info/SOURCES.txt
theeng.egg-info/dependency_links.txt
theeng.egg-info/requires.txt
theeng.egg-info/top_level.txt
theeng/algorithms/__init__.py
theeng/algorithms/optimizers.py
theeng/algorithms/rankers.py
theeng/algorithms/samplers.py
theeng/algorithms/simulators.py
theeng/algorithms/surrogates.py
theeng/algorithms/visualizations.py
theeng/core/__init__.py
theeng/core/abstract.py
theeng/core/optimizer.py
theeng/core/problem.py
theeng/core/ranker.py
theeng/core/sampler.py
theeng/core/simulator.py
theeng/core/surrogate.py
theeng/core/visualization.py
theeng/ui/__init__.py
theeng/ui/web/__init__.py
theeng/ui/web/querySurrogate.py