Metadata-Version: 2.1
Name: theeng
Version: 1.0
Summary: General structure optimizer leveraging surrogates.
Home-page: https://github.com/massimobrivio/TheEng
Author: Massimo Brivio
Author-email: m.g.brivio@gmail.com
License: UNKNOWN
Platform: UNKNOWN
